nanovdb_editor/__init__.py
nanovdb_editor/compiler.py
nanovdb_editor/compute.py
nanovdb_editor/device.py
nanovdb_editor/editor.py
nanovdb_editor/include/nanovdb/PNanoVDB.h
nanovdb_editor/include/nanovdb/putil/IO.h
nanovdb_editor/include/nanovdb_editor/PNanoVDBExt.h
nanovdb_editor/include/nanovdb_editor/putil/Camera.h
nanovdb_editor/include/nanovdb_editor/putil/Compiler.h
nanovdb_editor/include/nanovdb_editor/putil/Compute.h
nanovdb_editor/include/nanovdb_editor/putil/Convert.h
nanovdb_editor/include/nanovdb_editor/putil/Editor.h
nanovdb_editor/include/nanovdb_editor/putil/FileFormat.h
nanovdb_editor/include/nanovdb_editor/putil/GridBuild.h
nanovdb_editor/include/nanovdb_editor/putil/Loader.h
nanovdb_editor/include/nanovdb_editor/putil/ParallelPrimitives.h
nanovdb_editor/include/nanovdb_editor/putil/Raster.h
nanovdb_editor/include/nanovdb_editor/putil/Reflect.h
nanovdb_editor/include/nanovdb_editor/putil/Shader.hpp
nanovdb_editor/include/nanovdb_editor/putil/ThreadPool.hpp
nanovdb_editor/include/nanovdb_editor/putil/WorkerThread.hpp
nanovdb_editor/lib/glfw3.dll
nanovdb_editor/lib/pnanovdbcompiler.dll
nanovdb_editor/lib/pnanovdbcompiler.lib
nanovdb_editor/lib/pnanovdbcompute.dll
nanovdb_editor/lib/pnanovdbcompute.lib
nanovdb_editor/lib/pnanovdbeditor.dll
nanovdb_editor/lib/pnanovdbeditor.lib
nanovdb_editor/lib/pnanovdbfileformat.dll
nanovdb_editor/lib/pnanovdbfileformat.lib
nanovdb_editor/lib/slang-glslang.dll
nanovdb_editor/lib/slang-llvm.dll
nanovdb_editor/lib/slang.dll
nanovdb_editor/lib/vulkan-1.dll
nanovdb_editor/raster.py
nanovdb_editor/run_editor.py
nanovdb_editor/shaders/compute/clear_buffer.slang
nanovdb_editor/shaders/editor/editor.slang
nanovdb_editor/shaders/editor/editor.slang.json
nanovdb_editor/shaders/editor/editor_group.json
nanovdb_editor/shaders/editor/image2d.slang
nanovdb_editor/shaders/editor/image2d.slang.json
nanovdb_editor/shaders/editor/node2_verify_gpu.slang
nanovdb_editor/shaders/editor/node2_verify_gpu_onindex.slang
nanovdb_editor_dev-0.0.19.dist-info/METADATA
nanovdb_editor_dev-0.0.19.dist-info/WHEEL
nanovdb_editor_dev-0.0.19.dist-info/RECORD
