Metadata-Version: 2.2
Name: nanovdb-editor-dev
Version: 0.0.19
Summary: NanoVDB Editor Python Module
Keywords: nanovdb,volume,rendering,gaussian,splatting,3d
Author: The OpenVDB Project contributors
License: Apache-2.0
Project-URL: Homepage, https://github.com/openvdb/nanovdb-editor
Project-URL: Repository, https://github.com/openvdb/nanovdb-editor
Project-URL: Documentation, https://github.com/openvdb/nanovdb-editor/tree/main/pymodule
Requires-Python: >=3.8
